<?xml version="1.0" encoding="ISO-8859-1"?>
<semantic_density>

<text_level_sdis id="outs/'Bad to the Bone Lyrics.txt'" general_sdi="2.986359769096368" mean_char_leng="0.3184138262246585" propositional_negs="2" negative_sentiment_words="16" positive_sentiment_words="19" deep_conceptual_index="167.61904761904765" token_rare_words_ratio="0.026455026455026454" token_type_ratio="0.544973544973545" RID_category_ratio="[19-primary/0.5277777777777778,[abstract_tought,abstract_tought,abstract_tought,abstract_tought,aggression,concreteness,concreteness,concreteness,depth,expressive_beh,glory,hard,hard,narcissism,narcissism,narcissism,narcissism,narcissism,passivity,passivity,passivity,sadness,social_behavior,social_behavior,sound,temporal_repere,temporal_repere,temporal_repere,temporal_repere,temporal_repere,temporal_repere,temporal_repere,touch,vision,vision,vision]]" semantic_cohesion="0"></text_level_sdis>
<verse_sdi_vars ids="28">
<verse_sdi_var id="Bad to the Bone Lyrics.txt_1">
<sdivars id="1" tokens="9" mean_chars_leng="1.2857142857142858" verbs="0" chunks="8" verb_preds="0" concepts="3" domain_bound="3" adjectives="2" abstract_words="1-[0-bad-[abstract,stato]]/0" modal_advs_adjs="1" untensed_verbs="0" dense_constituents="0" tot_negs="1.2222222222222223" tot_pos="0" ratio_pos-negs="1.2222222222222223" negative_affect_words="[bad]" negative_polar_words="[bad]" abstract_eventiv_words="[bad/0]">bad to the Bone Lyrics by Running Wild . </sdivars>
</verse_sdi_var>
<verse_sdi_var id="Bad to the Bone Lyrics.txt_2">
<sdivars id="2" tokens="9" mean_chars_leng="0" verbs="1" chunks="5" verb_preds="0" concepts="1" domain_bound="0" adjectives="0" abstract_words="1-[5-war-[astratto,evento,attivita]]/1" modal_advs_adjs="0" untensed_verbs="1" dense_constituents="0" tot_negs="1" tot_pos="0.1111111111111111" ratio_pos-negs="0.1111111111111111" negative_affect_words="[war]" negative_polar_words="[war]" abstract_eventiv_words="[war/5]" concrete_words="[world/1]">fifty years ago with the world at war . </sdivars>
</verse_sdi_var>
<verse_sdi_var id="Bad to the Bone Lyrics.txt_3">
<sdivars id="3" tokens="5" mean_chars_leng="0.3333333333333333" verbs="1" chunks="4" verb_preds="1" concepts="2" domain_bound="1" adjectives="1" abstract_words="1-[3-devastated-[abstract,time,attivita,evento]]/1" modal_advs_adjs="0" untensed_verbs="0" dense_constituents="0" tot_negs="0.7" tot_pos="0.45" ratio_pos-negs="0.435483870967742" negative_affect_words="[devastated]" negative_polar_words="[devastated]" positive_polar_words="[hands]" abstract_eventiv_words="[devastated/3]" concrete_words="[hands/1]">hands bloodied   - devastated . </sdivars>
</verse_sdi_var>
<verse_sdi_var id="Bad to the Bone Lyrics.txt_4">
<sdivars id="4" tokens="8" mean_chars_leng="0.5" verbs="2" chunks="11" verb_preds="2" concepts="1" domain_bound="0" adjectives="1" abstract_words="1-[0-believe-[abstract,stato]]/0" modal_advs_adjs="1" untensed_verbs="0" dense_constituents="0" tot_negs="1.125" tot_pos="0.25" ratio_pos-negs="0.15384615384615385" positive_polar_words="[believe]" abstract_eventiv_words="[believe/0]">better believe they-re back for more . </sdivars>
</verse_sdi_var>
<verse_sdi_var id="Bad to the Bone Lyrics.txt_5">
<sdivars id="5" tokens="9" mean_chars_leng="1.125" verbs="1" chunks="6" verb_preds="0" concepts="3" domain_bound="1" adjectives="0" abstract_words="0-[]/2" modal_advs_adjs="0" untensed_verbs="1" dense_constituents="0.3333333333333333" tot_negs="1.3333333333333333" tot_pos="0.1111111111111111" ratio_pos-negs="0.04519774011299435" negative_affect_words="[fist]" negative_polar_words="[fist,pounding]" concrete_words="[world/1,steel/1]">pounding the world with a fist of steel . </sdivars>
</verse_sdi_var>
<verse_sdi_var id="Bad to the Bone Lyrics.txt_6">
<sdivars id="6" tokens="6" mean_chars_leng="0" verbs="1" chunks="5" verb_preds="1" concepts="2" domain_bound="1" adjectives="1" abstract_words="1-[8-heavy-[valutativo]]/2" modal_advs_adjs="0" untensed_verbs="0" dense_constituents="0" tot_negs="0.6666666666666666" tot_pos="0.3666666666666667" ratio_pos-negs="0.55" negative_affect_words="[heavy]" negative_polar_words="[heavy]" positive_polar_words="[handed]" abstract_eventiv_words="[heavy/8]" concrete_words="[jack/1,booted/1]">jack booted , heavy handed . </sdivars>
</verse_sdi_var>
<verse_sdi_var id="Bad to the Bone Lyrics.txt_7">
<sdivars id="7" tokens="7" mean_chars_leng="0.875" verbs="1" chunks="6" verb_preds="1" concepts="0" domain_bound="0" adjectives="1" abstract_words="3-[0-careless-[abstract,stato],5-pain-[astratto,evento,attivita],3-feel-[abstract,time,attivita,evento]]/0" modal_advs_adjs="0" untensed_verbs="0" dense_constituents="0.3333333333333333" tot_negs="0.47619047619047616" tot_pos="0.14285714285714285" ratio_pos-negs="0.10572687224669604" negative_affect_words="[careless,pain]" negative_polar_words="[careless,pain]" positive_polar_words="[feel]" abstract_eventiv_words="[careless/0,pain/5,feel/3]">careless of the pain we feel . </sdivars>
</verse_sdi_var>
<verse_sdi_var id="Bad to the Bone Lyrics.txt_8">
<sdivars id="8" tokens="6" mean_chars_leng="0.4375" verbs="1" chunks="7" verb_preds="0" concepts="2" domain_bound="0" adjectives="0" abstract_words="2-[5-bastards-[astratto,evento,attivita],14-life-[any,astratto,attivita,cambia,informa,stato,tempo,umano]]/0" modal_advs_adjs="0" untensed_verbs="1" dense_constituents="0" tot_negs="1" tot_pos="0.16666666666666666" ratio_pos-negs="0.11594202898550723" abstract_eventiv_words="[bastards/5,life/14]">bastards   - throwing life away . </sdivars>
</verse_sdi_var>
<verse_sdi_var id="Bad to the Bone Lyrics.txt_9">
<sdivars id="9" tokens="5" mean_chars_leng="0.8571428571428571" verbs="0" chunks="4" verb_preds="0" concepts="1" domain_bound="1" adjectives="1" abstract_words="2-[5-killers-[astratto,evento,attivita],5-alive-[astratto,evento,attivita]]/0" modal_advs_adjs="0" untensed_verbs="0" dense_constituents="0" tot_negs="1.2" tot_pos="0" ratio_pos-negs="1.2" positive_polar_words="[alive]" abstract_eventiv_words="[killers/5,alive/5]">killers   - alive today . </sdivars>
</verse_sdi_var>
<verse_sdi_var id="Bad to the Bone Lyrics.txt_10">
<sdivars id="10" tokens="5" mean_chars_leng="0" verbs="0" chunks="5" verb_preds="0" concepts="0" domain_bound="0" adjectives="0" abstract_words="0-[]/0" modal_advs_adjs="0" untensed_verbs="0" dense_constituents="0.5" tot_negs="0.5" tot_pos="0" ratio_pos-negs="0.5" positive_affect_words="[oh,oh,oh,oh]" positive_polar_words="[oh,oh,oh,oh]">oh oh oh oh . </sdivars>
</verse_sdi_var>
<verse_sdi_var id="Bad to the Bone Lyrics.txt_11">
<sdivars id="11" tokens="5" mean_chars_leng="0" verbs="2" chunks="6" verb_preds="1" concepts="0" domain_bound="0" adjectives="0" abstract_words="2-[3-tell-[abstract,time,attivita,evento],5-lies-[astratto,evento,attivita]]/0" modal_advs_adjs="0" untensed_verbs="0" dense_constituents="0" tot_negs="0" tot_pos="0.16666666666666666" ratio_pos-negs="0.16666666666666666" negative_affect_words="[no]" negative_polar_words="[no,no,lies]" abstract_eventiv_words="[tell/3,lies/5]">don-t tell no lies . </sdivars>
</verse_sdi_var>
<verse_sdi_var id="Bad to the Bone Lyrics.txt_12">
<sdivars id="12" tokens="6" mean_chars_leng="0.8571428571428571" verbs="1" chunks="5" verb_preds="1" concepts="1" domain_bound="0" adjectives="0" abstract_words="1-[5-see-[astratto,evento,attivita]]/1" modal_advs_adjs="0" untensed_verbs="0" dense_constituents="0" tot_negs="0" tot_pos="0.2" ratio_pos-negs="0.23333333333333336" positive_polar_words="[eyes]" abstract_eventiv_words="[see/5]" concrete_words="[eyes/1]">i see through your eyes . </sdivars>
</verse_sdi_var>
<verse_sdi_var id="Bad to the Bone Lyrics.txt_13">
<sdivars id="13" tokens="7" mean_chars_leng="0" verbs="2" chunks="5" verb_preds="1" concepts="1" domain_bound="0" adjectives="1" abstract_words="2-[0-bad-[abstract,stato],1-bone-[astratto,body_part,sostanza,umano]]/0" modal_advs_adjs="1" untensed_verbs="0" dense_constituents="0" tot_negs="0.14285714285714285" tot_pos="0.2857142857142857" ratio_pos-negs="2.0" negative_affect_words="[bad]" negative_polar_words="[bad]" positive_polar_words="[bone]" abstract_eventiv_words="[bad/0,bone/1]">you-re bad to the bone . </sdivars>
</verse_sdi_var>
<verse_sdi_var id="Bad to the Bone Lyrics.txt_14">
<sdivars id="14" tokens="5" mean_chars_leng="0" verbs="0" chunks="5" verb_preds="0" concepts="0" domain_bound="0" adjectives="0" abstract_words="0-[]/0" modal_advs_adjs="0" untensed_verbs="0" dense_constituents="0.5" tot_negs="0.5" tot_pos="0" ratio_pos-negs="0.5" positive_affect_words="[oh,oh,oh,oh]" positive_polar_words="[oh,oh,oh,oh]">oh oh oh oh . </sdivars>
</verse_sdi_var>
<verse_sdi_var id="Bad to the Bone Lyrics.txt_15">
<sdivars id="15" tokens="5" mean_chars_leng="0" verbs="2" chunks="6" verb_preds="1" concepts="0" domain_bound="0" adjectives="0" abstract_words="2-[3-tell-[abstract,time,attivita,evento],5-lies-[astratto,evento,attivita]]/0" modal_advs_adjs="0" untensed_verbs="0" dense_constituents="0" tot_negs="0" tot_pos="0.16666666666666666" ratio_pos-negs="0.16666666666666666" negative_affect_words="[no]" negative_polar_words="[no,no,lies]" abstract_eventiv_words="[tell/3,lies/5]">don-t tell no lies . </sdivars>
</verse_sdi_var>
<verse_sdi_var id="Bad to the Bone Lyrics.txt_16">
<sdivars id="16" tokens="8" mean_chars_leng="0" verbs="2" chunks="7" verb_preds="1" concepts="1" domain_bound="0" adjectives="0" abstract_words="2-[5-hear-[astratto,evento,attivita],5-cries-[astratto,evento,attivita]]/0" modal_advs_adjs="0" untensed_verbs="0" dense_constituents="0" tot_negs="1" tot_pos="0.14285714285714285" ratio_pos-negs="0.14285714285714285" negative_polar_words="[cries]" abstract_eventiv_words="[hear/5,cries/5]">you can-t hear the cries ' . </sdivars>
</verse_sdi_var>
<verse_sdi_var id="Bad to the Bone Lyrics.txt_17">
<sdivars id="17" tokens="8" mean_chars_leng="0" verbs="2" chunks="6" verb_preds="1" concepts="2" domain_bound="1" adjectives="1" abstract_words="2-[0-bad-[abstract,stato],1-bone-[astratto,body_part,sostanza,umano]]/0" modal_advs_adjs="1" untensed_verbs="0" dense_constituents="0" tot_negs="0.625" tot_pos="0.41666666666666663" ratio_pos-negs="0.6666666666666666" negative_affect_words="[bad]" negative_polar_words="[bad]" positive_polar_words="[bone]" abstract_eventiv_words="[bad/0,bone/1]">Cos you-re bad to the bone . </sdivars>
</verse_sdi_var>
<verse_sdi_var id="Bad to the Bone Lyrics.txt_18">
<sdivars id="18" tokens="8" mean_chars_leng="1.1428571428571428" verbs="4" chunks="11" verb_preds="2" concepts="0" domain_bound="0" adjectives="0" abstract_words="2-[3-changed-[abstract,time,attivita,evento],0-know-[abstract,stato]]/0" modal_advs_adjs="0" untensed_verbs="0" dense_constituents="0" tot_negs="1" tot_pos="0.18181818181818182" ratio_pos-negs="0.08484848484848485" positive_polar_words="[changed,know]" abstract_eventiv_words="[changed/3,know/0]">times have changed but he don-t know . </sdivars>
</verse_sdi_var>
<verse_sdi_var id="Bad to the Bone Lyrics.txt_19">
<sdivars id="19" tokens="6" mean_chars_leng="0" verbs="0" chunks="4" verb_preds="0" concepts="2" domain_bound="1" adjectives="0" abstract_words="1-[5-black-[astratto,evento,attivita]]/2" modal_advs_adjs="0" untensed_verbs="0" dense_constituents="1" tot_negs="2.5" tot_pos="0" ratio_pos-negs="1.5" negative_affect_words="[black]" negative_polar_words="[black,zoot]" positive_polar_words="[suit,tie]" abstract_eventiv_words="[black/5]" concrete_words="[suit/1,tie/2]">zoot suit , black tie . </sdivars>
</verse_sdi_var>
<verse_sdi_var id="Bad to the Bone Lyrics.txt_20">
<sdivars id="20" tokens="7" mean_chars_leng="0.875" verbs="1" chunks="7" verb_preds="1" concepts="3" domain_bound="2" adjectives="2" abstract_words="3-[3-careless-[evaluative],5-lies-[astratto,evento,attivita],9-low-[astratto,stato]]/0" modal_advs_adjs="0" untensed_verbs="0" dense_constituents="0" tot_negs="0.9523809523809523" tot_pos="0.2857142857142857" ratio_pos-negs="0.1563517915309446" negative_affect_words="[careless]" negative_polar_words="[careless,lies]" abstract_eventiv_words="[careless/3,lies/5,low/9]">careless that the lies are low . </sdivars>
</verse_sdi_var>
<verse_sdi_var id="Bad to the Bone Lyrics.txt_21">
<sdivars id="21" tokens="6" mean_chars_leng="0.5454545454545454" verbs="0" chunks="11" verb_preds="0" concepts="1" domain_bound="1" adjectives="0" abstract_words="1-[1-one_for_all-[astratto,nquant]]/0" modal_advs_adjs="0" untensed_verbs="0" dense_constituents="0" tot_negs="3" tot_pos="0" ratio_pos-negs="3" abstract_eventiv_words="[one_for_all/1]">one_for_all and all for one . </sdivars>
</verse_sdi_var>
<verse_sdi_var id="Bad to the Bone Lyrics.txt_22">
<sdivars id="22" tokens="6" mean_chars_leng="1" verbs="1" chunks="5" verb_preds="1" concepts="2" domain_bound="1" adjectives="2" abstract_words="3-[8-smooth-[attivita],5-hidden-[astratto,evento,attivita],6-truth-[astratto,attivita,informa,stato]]/0" modal_advs_adjs="0" untensed_verbs="0" dense_constituents="0" tot_negs="0.8333333333333333" tot_pos="0.3666666666666667" ratio_pos-negs="0.2" negative_polar_words="[hidden]" positive_polar_words="[talking,smooth,truth]" abstract_eventiv_words="[smooth/8,hidden/5,truth/6]">talking smooth   - hidden truth . </sdivars>
</verse_sdi_var>
<verse_sdi_var id="Bad to the Bone Lyrics.txt_23">
<sdivars id="23" tokens="6" mean_chars_leng="0.8571428571428571" verbs="2" chunks="7" verb_preds="1" concepts="1" domain_bound="1" adjectives="0" abstract_words="1-[3-begun-[abstract,time,attivita,evento]]/1" modal_advs_adjs="0" untensed_verbs="1" dense_constituents="0" tot_negs="1" tot_pos="0.14285714285714285" ratio_pos-negs="0.07692307692307691" negative_affect_words="[bomb]" negative_polar_words="[bomb,ticking]" positive_polar_words="[begun]" abstract_eventiv_words="[begun/3]" concrete_words="[bomb/1]">time bomb ticking just begun . </sdivars>
</verse_sdi_var>
<verse_sdi_var id="Bad to the Bone Lyrics.txt_24">
<sdivars id="24" tokens="8" mean_chars_leng="1" verbs="2" chunks="10" verb_preds="1" concepts="1" domain_bound="0" adjectives="0" abstract_words="1-[5-see-[astratto,evento,attivita]]/1" modal_advs_adjs="0" untensed_verbs="1" dense_constituents="0" tot_negs="2" tot_pos="0.1" ratio_pos-negs="0.03333333333333333" negative_affect_words="[alone]" negative_polar_words="[alone]" positive_polar_words="[standing]" abstract_eventiv_words="[see/5]" concrete_words="[world/1]">standing alone for the world to see . </sdivars>
</verse_sdi_var>
<verse_sdi_var id="Bad to the Bone Lyrics.txt_25">
<sdivars id="25" tokens="5" mean_chars_leng="0.45454545454545453" verbs="1" chunks="5" verb_preds="1" concepts="2" domain_bound="1" adjectives="1" abstract_words="2-[5-non-starter-[astratto,evento,attivita],3-harder-[evaluative]]/0" modal_advs_adjs="0" untensed_verbs="0" dense_constituents="0" tot_negs="0.7" tot_pos="0.4" ratio_pos-negs="0.3464566929133858" positive_polar_words="[push]" abstract_eventiv_words="[non-starter/5,harder/3]">non-starter - push harder . </sdivars>
</verse_sdi_var>
<verse_sdi_var id="Bad to the Bone Lyrics.txt_26">
<sdivars id="26" tokens="8" mean_chars_leng="1" verbs="3" chunks="13" verb_preds="2" concepts="0" domain_bound="0" adjectives="0" abstract_words="2-[0-believes-[abstract,stato],3-come-[abstract,time,attivita,evento]]/0" modal_advs_adjs="2" untensed_verbs="1" dense_constituents="0" tot_negs="2" tot_pos="0.15384615384615385" ratio_pos-negs="0.05128205128205129" positive_polar_words="[believes]" abstract_eventiv_words="[believes/0,come/3]">he still believes his time will come . </sdivars>
</verse_sdi_var>
<verse_sdi_var id="Bad to the Bone Lyrics.txt_27">
<sdivars id="27" tokens="6" mean_chars_leng="1" verbs="0" chunks="4" verb_preds="0" concepts="2" domain_bound="2" adjectives="2" abstract_words="3-[5-small-[astratto,evento,attivita],0-wonder-[abstract,stato],3-old-[abstract,time,attivita,evento]]/0" modal_advs_adjs="0" untensed_verbs="0" dense_constituents="1" tot_negs="2.333333333333333" tot_pos="0" ratio_pos-negs="1.3333333333333333" negative_polar_words="[wonder,thunder]" abstract_eventiv_words="[small/5,wonder/0,old/3]">small wonder   - old thunder . </sdivars>
</verse_sdi_var>
<verse_sdi_var id="Bad to the Bone Lyrics.txt_28">
<sdivars id="28" tokens="9" mean_chars_leng="0" verbs="3" chunks="16" verb_preds="3" concepts="0" domain_bound="0" adjectives="0" abstract_words="2-[5-see-[astratto,evento,attivita],0-wrong-[abstract,stato]]/0" modal_advs_adjs="0" untensed_verbs="1" dense_constituents="0" tot_negs="2" tot_pos="0.1875" ratio_pos-negs="0.09375" negative_affect_words="[wrong]" negative_polar_words="[wrong]" abstract_eventiv_words="[see/5,wrong/0]">can-t he see that he-s wrong . </sdivars>
</verse_sdi_var>
</verse_sdi_vars>
</semantic_density>
