<?xml version="1.0" encoding="ISO-8859-1"?>
<semantic_density>

<text_level_sdis id="outs/'Midnight Cypher at 9.txt'" general_sdi="8.854375679083518" mean_char_leng="0.5461927081647913" propositional_negs="5" negative_sentiment_words="54" positive_sentiment_words="94" deep_conceptual_index="987.9369747899161" token_rare_words_ratio="0.05" token_type_ratio="0.49696969696969695" RID_category_ratio="[59-primary/0.4957983193277311,[abstract_tought,abstract_tought,abstract_tought,abstract_tought,abstract_tought,abstract_tought,abstract_tought,abstract_tought,affection,affection,affection,affection,affection,affection,affection,affection,affection,affection,aggression,aggression,aggression,aggression,aggression,aggression,aggression,aggression,aggression,aggression,anality,anality,ascend,brink-passage,brink-passage,brink-passage,cold,cold,concreteness,concreteness,concreteness,concreteness,concreteness,concreteness,concreteness,concreteness,concreteness,concreteness,concreteness,concreteness,concreteness,concreteness,diffusion,expressive_beh,expressive_beh,expressive_beh,fire,fire,gen_sensation,glory,hard,hard,height,height,height,height,instru_behavior,instru_behavior,instru_behavior,moral_imperative,moral_imperative,narcissism,narcissism,narcissism,narcissism,narcissism,narcissism,narcissism,narcissism,narcissism,narcissism,orality,orality,orality,passivity,passivity,positive_affect,positive_affect,random_movement,restraint,restraint,restraint,restraint,restraint,sex,sex,sex,sex,sex,social_behavior,social_behavior,social_behavior,social_behavior,social_behavior,social_behavior,social_behavior,soft,temporal_repere,temporal_repere,temporal_repere,temporal_repere,temporal_repere,temporal_repere,temporal_repere,temporal_repere,temporal_repere,unknow,vision,vision,vision,vision]]" semantic_cohesion="0"></text_level_sdis>
<verse_sdi_vars ids="42">
<verse_sdi_var id="Midnight Cypher at 9.txt_1">
<sdivars id="1" tokens="10" mean_chars_leng="0.625" verbs="1" chunks="8" verb_preds="1" concepts="3" domain_bound="2" adjectives="0" abstract_words="3-[8-midnight-[tempo],5-work-[astratto,evento,attivita],8-progress-[attivita,evento]]/0" modal_advs_adjs="0" untensed_verbs="0" dense_constituents="0.2" tot_negs="1.2" tot_pos="0.125" ratio_pos-negs="0.0684931506849315" positive_polar_words="[midnight,work]" abstract_eventiv_words="[midnight/8,work/5,progress/8]">midnight Cypher at 9 by Work ' n Progress . </sdivars>
</verse_sdi_var>
<verse_sdi_var id="Midnight Cypher at 9.txt_2">
<sdivars id="2" tokens="4" mean_chars_leng="0.4" verbs="0" chunks="4" verb_preds="0" concepts="0" domain_bound="0" adjectives="0" abstract_words="1-[5-background-[astratto,evento,attivita]]/0" modal_advs_adjs="0" untensed_verbs="0" dense_constituents="0" tot_negs="0" tot_pos="0" ratio_pos-negs="0" positive_polar_words="[background]" abstract_eventiv_words="[background/5]">background Nikko B . </sdivars>
</verse_sdi_var>
<verse_sdi_var id="Midnight Cypher at 9.txt_3">
<sdivars id="3" tokens="2" mean_chars_leng="0" verbs="0" chunks="4" verb_preds="0" concepts="0" domain_bound="0" adjectives="0" abstract_words="0-[]/0" modal_advs_adjs="0" untensed_verbs="0" dense_constituents="0" tot_negs="0" tot_pos="0" ratio_pos-negs="0">S . </sdivars>
</verse_sdi_var>
<verse_sdi_var id="Midnight Cypher at 9.txt_4">
<sdivars id="4" tokens="12" mean_chars_leng="0" verbs="2" chunks="14" verb_preds="2" concepts="2" domain_bound="1" adjectives="0" abstract_words="1-[10-dude-[relat,sociale,umano]]/0" modal_advs_adjs="0" untensed_verbs="0" dense_constituents="0" tot_negs="1" tot_pos="0.14285714285714285" ratio_pos-negs="0.14285714285714285" positive_polar_words="[dude,do_it]" abstract_eventiv_words="[dude/10]">this is the last time dude if , I don-t do_it . </sdivars>
</verse_sdi_var>
<verse_sdi_var id="Midnight Cypher at 9.txt_5">
<sdivars id="5" tokens="4" mean_chars_leng="0" verbs="2" chunks="5" verb_preds="1" concepts="0" domain_bound="0" adjectives="0" abstract_words="0-[]/0" modal_advs_adjs="0" untensed_verbs="0" dense_constituents="0" tot_negs="0" tot_pos="0.2" ratio_pos-negs="0.2">I-M done . </sdivars>
</verse_sdi_var>
<verse_sdi_var id="Midnight Cypher at 9.txt_6">
<sdivars id="6" tokens="39" mean_chars_leng="0.8181818181818182" verbs="10" chunks="33" verb_preds="4" concepts="9" domain_bound="5" adjectives="1" abstract_words="9-[11-name-[attivita,informa,stato,umano],1-self-explanatory-[astratto,umano],3-getting-[abstract,time,attivita,evento],5-judged-[astratto,evento,attivita],5-fucking-[astratto,evento,attivita],9-attack-[attivita,stato],3-get-[abstract,time,attivita,evento],3-rid-[abstract,time,attivita,evento],5-fucking-[astratto,evento,attivita]]/4" modal_advs_adjs="0" untensed_verbs="2" dense_constituents="0.08333333333333333" tot_negs="4.664529914529915" tot_pos="0.3776223776223776" ratio_pos-negs="0.06887511071744906" negative_affect_words="[fucking,attack,dying,rid,fucking]" negative_polar_words="[fucking,attack,dying,rid,fucking,getting,jury,get,cops]" positive_polar_words="[name,self-explanatory,judged,nurse,like]" abstract_eventiv_words="[name/11,self-explanatory/1,getting/3,judged/5,fucking/5,attack/9,get/3,rid/3,fucking/5]" concrete_words="[court/2,jury/1,gurney/1,cops/1]">my name is Ody self-explanatory , in court , getting judged by the fucking jury attack your nurse , while I-m dying on a gurney i can-t get rid of the cops like they-re fucking . </sdivars>
</verse_sdi_var>
<verse_sdi_var id="Midnight Cypher at 9.txt_7">
<sdivars id="7" tokens="53" mean_chars_leng="1.1363636363636365" verbs="8" chunks="27" verb_preds="2" concepts="18" domain_bound="8" adjectives="1" abstract_words="12-[0-fakes-[abstract,stato],5-playing-[astratto,evento,attivita],1-mother-[astratto,body_part,sostanza,umano],10-play-[attivita,informa,stato],5-praying-[astratto,evento,attivita],3-thinking-[abstract,time,attivita,evento],9-fund-[astratto,oggetto],5-going-[astratto,evento,attivita],7-straight-[istituzione],5-double-[astratto,evento,attivita],3-please-[istituzione],5-stop-[astratto,evento,attivita]]/5" modal_advs_adjs="0" untensed_verbs="3" dense_constituents="0.06666666666666667" tot_negs="8.529979035639414" tot_pos="0.22501747030048916" ratio_pos-negs="0.023278449557992055" negative_affect_words="[double,stop]" negative_polar_words="[double,stop,fakes]" positive_polar_words="[like,mother,play,praying,thinking,college,fund,straight,please]" abstract_eventiv_words="[fakes/0,playing/5,mother/1,play/10,praying/5,thinking/3,fund/9,going/5,straight/7,double/5,please/3,stop/5]" concrete_words="[church/1,knees/1,church/1,college/1,B/2]">Herpes they-re all fakes like a church , sleeze playing , mother , Mary after she-s on her knees , at the church play , praying over STD-s , while she-s thinking about her college fund , going straight to double D-s Jeez please , just stop the B . </sdivars>
</verse_sdi_var>
<verse_sdi_var id="Midnight Cypher at 9.txt_8">
<sdivars id="8" tokens="8" mean_chars_leng="0" verbs="2" chunks="9" verb_preds="1" concepts="1" domain_bound="1" adjectives="0" abstract_words="0-[]/0" modal_advs_adjs="1" untensed_verbs="0" dense_constituents="0" tot_negs="1" tot_pos="0.1111111111111111" ratio_pos-negs="0.1111111111111111" negative_affect_words="[not]" negative_polar_words="[not,not]" positive_polar_words="[like]">S you may not like me cuz . </sdivars>
</verse_sdi_var>
<verse_sdi_var id="Midnight Cypher at 9.txt_9">
<sdivars id="9" tokens="7" mean_chars_leng="0" verbs="1" chunks="6" verb_preds="1" concepts="1" domain_bound="1" adjectives="0" abstract_words="0-[]/1" modal_advs_adjs="0" untensed_verbs="0" dense_constituents="0" tot_negs="0" tot_pos="0.16666666666666666" ratio_pos-negs="0.16666666666666666" negative_polar_words="[chest]" concrete_words="[chest/1]">It-S me inside my chest : </sdivars>
</verse_sdi_var>
<verse_sdi_var id="Midnight Cypher at 9.txt_10">
<sdivars id="10" tokens="4" mean_chars_leng="0" verbs="0" chunks="5" verb_preds="0" concepts="0" domain_bound="0" adjectives="0" abstract_words="0-[]/0" modal_advs_adjs="0" untensed_verbs="0" dense_constituents="0" tot_negs="1" tot_pos="0" ratio_pos-negs="1">but with me . </sdivars>
</verse_sdi_var>
<verse_sdi_var id="Midnight Cypher at 9.txt_11">
<sdivars id="11" tokens="22" mean_chars_leng="1.4" verbs="4" chunks="31" verb_preds="3" concepts="2" domain_bound="2" adjectives="2" abstract_words="4-[5-see-[astratto,evento,attivita],3-get-[abstract,time,attivita,evento],8-secret-[attivita,informa],7-kept-[evaluative]]/1" modal_advs_adjs="1" untensed_verbs="0" dense_constituents="0" tot_negs="3.090909090909091" tot_pos="0.2785923753665689" ratio_pos-negs="0.062034739454094295" negative_affect_words="[exactly,secret]" negative_polar_words="[exactly,secret,get]" positive_polar_words="[decent,person,kept]" abstract_eventiv_words="[see/5,get/3,secret/8,kept/7]" concrete_words="[person/1]">What you see is exactly what you get and , I-m actually a decent person best secret kept yet but . </sdivars>
</verse_sdi_var>
<verse_sdi_var id="Midnight Cypher at 9.txt_12">
<sdivars id="12" tokens="7" mean_chars_leng="0.75" verbs="2" chunks="9" verb_preds="2" concepts="0" domain_bound="0" adjectives="0" abstract_words="1-[3-shies-[abstract,time,attivita,evento]]/0" modal_advs_adjs="0" untensed_verbs="0" dense_constituents="0" tot_negs="0" tot_pos="0.2222222222222222" ratio_pos-negs="0.2962962962962963" negative_polar_words="[shies]" positive_polar_words="[like]" abstract_eventiv_words="[shies/3]">Everyone shies away like I-m : </sdivars>
</verse_sdi_var>
<verse_sdi_var id="Midnight Cypher at 9.txt_13">
<sdivars id="13" tokens="22" mean_chars_leng="0.5238095238095238" verbs="4" chunks="17" verb_preds="3" concepts="6" domain_bound="3" adjectives="2" abstract_words="6-[0-deranged-[abstract,stato],1-mind-s-[astratto],0-emotional-[abstract,stato],0-vacate-[abstract,stato],3-got-[abstract,time,attivita,evento],8-older-[evaluative]]/1" modal_advs_adjs="0" untensed_verbs="0" dense_constituents="0.16666666666666666" tot_negs="1.7575757575757576" tot_pos="0.3582887700534759" ratio_pos-negs="0.1570487777653756" negative_affect_words="[deranged,emotional,vacate]" negative_polar_words="[deranged,emotional,vacate,got]" positive_polar_words="[brain,older]" abstract_eventiv_words="[deranged/0,mind-s/1,emotional/0,vacate/0,got/3,older/8]" concrete_words="[roller-coaster/1]">a deranged vet , my mind-s , a train-wreck emotional roller-coaster it , didn-t vacate my brain as I got older . </sdivars>
</verse_sdi_var>
<verse_sdi_var id="Midnight Cypher at 9.txt_14">
<sdivars id="14" tokens="12" mean_chars_leng="0.631578947368421" verbs="2" chunks="11" verb_preds="2" concepts="3" domain_bound="1" adjectives="1" abstract_words="4-[3-continue-[abstract,time,attivita,evento],3-soul-search-[abstract,time,attivita,evento],3-gets-[abstract,time,attivita,evento],9-colder-[istituzione,umano]]/1" modal_advs_adjs="0" untensed_verbs="0" dense_constituents="0" tot_negs="2.4166666666666665" tot_pos="0.3484848484848485" ratio_pos-negs="0.1143230869849575" negative_polar_words="[gets]" positive_polar_words="[continue]" abstract_eventiv_words="[continue/3,soul-search/3,gets/3,colder/9]" concrete_words="[world/1]">i continue to soul-search , but the world just gets colder . </sdivars>
</verse_sdi_var>
<verse_sdi_var id="Midnight Cypher at 9.txt_15">
<sdivars id="15" tokens="21" mean_chars_leng="1.3333333333333333" verbs="6" chunks="28" verb_preds="4" concepts="2" domain_bound="1" adjectives="0" abstract_words="5-[3-chilling-[abstract,time,attivita,evento],3-told-[abstract,time,attivita,evento],3-thought-[abstract,time,attivita,evento],8-minute-[tempo],3-said-[abstract,time,attivita,evento]]/1" modal_advs_adjs="0" untensed_verbs="1" dense_constituents="0" tot_negs="4" tot_pos="0.14285714285714285" ratio_pos-negs="0.026785714285714284" negative_affect_words="[chilling]" negative_polar_words="[chilling,spit]" positive_polar_words="[crew,told,thought,minute,said]" abstract_eventiv_words="[chilling/3,told/3,thought/3,minute/8,said/3]" concrete_words="[crew/1]">so I-m chilling with the crew and they told me to spit it thought for a minute then said : </sdivars>
</verse_sdi_var>
<verse_sdi_var id="Midnight Cypher at 9.txt_16">
<sdivars id="16" tokens="14" mean_chars_leng="0" verbs="2" chunks="10" verb_preds="1" concepts="1" domain_bound="0" adjectives="0" abstract_words="0-[]/1" modal_advs_adjs="0" untensed_verbs="1" dense_constituents="0.25" tot_negs="1.25" tot_pos="0.1" ratio_pos-negs="0.08" negative_affect_words="[bar]" negative_polar_words="[bar]" positive_affect_words="[yeah]" positive_polar_words="[yeah,rolled]" concrete_words="[bar/1]">yeah , I-m with it rolled up a bar and the O . </sdivars>
</verse_sdi_var>
<verse_sdi_var id="Midnight Cypher at 9.txt_17">
<sdivars id="17" tokens="2" mean_chars_leng="0" verbs="0" chunks="4" verb_preds="0" concepts="1" domain_bound="0" adjectives="0" abstract_words="0-[]/0" modal_advs_adjs="0" untensed_verbs="0" dense_constituents="0" tot_negs="0" tot_pos="0" ratio_pos-negs="0">G . </sdivars>
</verse_sdi_var>
<verse_sdi_var id="Midnight Cypher at 9.txt_18">
<sdivars id="18" tokens="3" mean_chars_leng="0" verbs="1" chunks="4" verb_preds="1" concepts="0" domain_bound="0" adjectives="0" abstract_words="0-[]/0" modal_advs_adjs="0" untensed_verbs="0" dense_constituents="0" tot_negs="0" tot_pos="0.25" ratio_pos-negs="0.25">lit it . </sdivars>
</verse_sdi_var>
<verse_sdi_var id="Midnight Cypher at 9.txt_19">
<sdivars id="19" tokens="10" mean_chars_leng="0.625" verbs="4" chunks="18" verb_preds="3" concepts="0" domain_bound="0" adjectives="0" abstract_words="1-[3-started-[abstract,time,attivita,evento]]/0" modal_advs_adjs="0" untensed_verbs="1" dense_constituents="0" tot_negs="1" tot_pos="0.16666666666666666" ratio_pos-negs="0.10256410256410256" positive_polar_words="[heads]" abstract_eventiv_words="[started/3]">passed it around and everybody hit it heads started . </sdivars>
</verse_sdi_var>
<verse_sdi_var id="Midnight Cypher at 9.txt_20">
<sdivars id="20" tokens="9" mean_chars_leng="0.5" verbs="2" chunks="11" verb_preds="0" concepts="4" domain_bound="2" adjectives="0" abstract_words="5-[5-bobbing-[astratto,evento,attivita],3-got-[abstract,time,attivita,evento],10-dope-[attivita,informa,oggetto,strumento],8-commandment-[attivita,informa],11-style-[animato,astratto,attivita,informa,plant]]/1" modal_advs_adjs="0" untensed_verbs="2" dense_constituents="0" tot_negs="2" tot_pos="0.2222222222222222" ratio_pos-negs="0.08888888888888888" negative_affect_words="[shit,dope]" negative_polar_words="[shit,dope,got]" positive_polar_words="[commandment,style]" abstract_eventiv_words="[bobbing/5,got/3,dope/10,commandment/8,style/11]" concrete_words="[dope/2]">Bobbing shit got dope , ten commandment style . </sdivars>
</verse_sdi_var>
<verse_sdi_var id="Midnight Cypher at 9.txt_21">
<sdivars id="21" tokens="6" mean_chars_leng="0" verbs="2" chunks="9" verb_preds="2" concepts="1" domain_bound="1" adjectives="0" abstract_words="0-[]/0" modal_advs_adjs="0" untensed_verbs="0" dense_constituents="0" tot_negs="0" tot_pos="0.2222222222222222" ratio_pos-negs="0.2222222222222222">This is what God wrote : </sdivars>
</verse_sdi_var>
<verse_sdi_var id="Midnight Cypher at 9.txt_22">
<sdivars id="22" tokens="9" mean_chars_leng="0" verbs="2" chunks="8" verb_preds="1" concepts="1" domain_bound="0" adjectives="1" abstract_words="3-[3-get-[abstract,time,attivita,evento],3-get-[abstract,time,attivita,evento],7-lost-[istituzione]]/0" modal_advs_adjs="0" untensed_verbs="0" dense_constituents="0" tot_negs="0.1111111111111111" tot_pos="0.2222222222222222" ratio_pos-negs="2.0" negative_affect_words="[lost]" negative_polar_words="[lost,get,get]" abstract_eventiv_words="[get/3,get/3,lost/7]">yo square get with it or get lost . </sdivars>
</verse_sdi_var>
<verse_sdi_var id="Midnight Cypher at 9.txt_23">
<sdivars id="23" tokens="38" mean_chars_leng="1.6818181818181819" verbs="8" chunks="28" verb_preds="2" concepts="7" domain_bound="5" adjectives="3" abstract_words="11-[9-steady-[relat,sociale,umano],3-getting-[abstract,time,attivita,evento],5-tossed-[astratto,evento,attivita],3-came-[abstract,time,attivita,evento],3-bring-[abstract,time,attivita,evento],8-real-[astratto,oggetto],3-brought-[abstract,time,attivita,evento],7-mind-[astratto],5-going-[astratto,evento,attivita],8-soft-[valutativo],5-core-[astratto,evento,attivita]]/1" modal_advs_adjs="0" untensed_verbs="3" dense_constituents="0" tot_negs="4.793233082706767" tot_pos="0.28195488721804507" ratio_pos-negs="0.04354481156972448" negative_affect_words="[mind,never,hard,hard]" negative_polar_words="[mind,never,hard,hard,never,getting,tossed]" positive_polar_words="[like,salad,steady,bring,real,like,soft,core,brain]" abstract_eventiv_words="[steady/9,getting/3,tossed/5,came/3,bring/3,real/8,brought/3,mind/7,going/5,soft/8,core/5]" concrete_words="[salad/1]">just like a salad , steady , getting tossed i came to bring the real , so it-s been brought mind like concrete , never going soft always hard to the core hard to the brain . </sdivars>
</verse_sdi_var>
<verse_sdi_var id="Midnight Cypher at 9.txt_24">
<sdivars id="24" tokens="5" mean_chars_leng="0.5714285714285714" verbs="2" chunks="5" verb_preds="1" concepts="0" domain_bound="0" adjectives="0" abstract_words="1-[5-fucking-[astratto,evento,attivita]]/0" modal_advs_adjs="0" untensed_verbs="0" dense_constituents="0" tot_negs="0" tot_pos="0.2" ratio_pos-negs="0.35000000000000003" negative_affect_words="[fucking]" negative_polar_words="[fucking]" abstract_eventiv_words="[fucking/5]">you-re fucking up . </sdivars>
</verse_sdi_var>
<verse_sdi_var id="Midnight Cypher at 9.txt_25">
<sdivars id="25" tokens="4" mean_chars_leng="0" verbs="1" chunks="4" verb_preds="1" concepts="0" domain_bound="0" adjectives="0" abstract_words="1-[5-go-[astratto,evento,attivita]]/0" modal_advs_adjs="0" untensed_verbs="0" dense_constituents="0" tot_negs="0" tot_pos="0.25" ratio_pos-negs="0.25" abstract_eventiv_words="[go/5]">My high go : </sdivars>
</verse_sdi_var>
<verse_sdi_var id="Midnight Cypher at 9.txt_26">
<sdivars id="26" tokens="5" mean_chars_leng="0.625" verbs="1" chunks="5" verb_preds="1" concepts="2" domain_bound="1" adjectives="0" abstract_words="1-[8-get-[informa,tecno]]/1" modal_advs_adjs="0" untensed_verbs="0" dense_constituents="0" tot_negs="0" tot_pos="0.2" ratio_pos-negs="0.32" negative_affect_words="[game]" negative_polar_words="[game,get]" positive_polar_words="[schooled]" abstract_eventiv_words="[get/8]" concrete_words="[game/2]">get schooled on game . </sdivars>
</verse_sdi_var>
<verse_sdi_var id="Midnight Cypher at 9.txt_27">
<sdivars id="27" tokens="11" mean_chars_leng="1.2222222222222223" verbs="2" chunks="9" verb_preds="2" concepts="5" domain_bound="2" adjectives="0" abstract_words="3-[3-got-[abstract,time,attivita,evento],5-knowledge-[astratto,informa,tecno],3-chill-[abstract,time,attivita,evento]]/1" modal_advs_adjs="0" untensed_verbs="0" dense_constituents="0.3333333333333333" tot_negs="0.3333333333333333" tot_pos="0.2222222222222222" ratio_pos-negs="0.14285714285714285" negative_affect_words="[chill]" negative_polar_words="[chill,got]" positive_polar_words="[street,knowledge]" abstract_eventiv_words="[got/3,knowledge/5,chill/3]" concrete_words="[street/2]">i got hella street knowledge cuz I chill with O . </sdivars>
</verse_sdi_var>
<verse_sdi_var id="Midnight Cypher at 9.txt_28">
<sdivars id="28" tokens="3" mean_chars_leng="0" verbs="0" chunks="4" verb_preds="0" concepts="1" domain_bound="0" adjectives="0" abstract_words="0-[]/0" modal_advs_adjs="0" untensed_verbs="0" dense_constituents="0" tot_negs="0" tot_pos="0" ratio_pos-negs="0">G ' . </sdivars>
</verse_sdi_var>
<verse_sdi_var id="Midnight Cypher at 9.txt_29">
<sdivars id="29" tokens="21" mean_chars_leng="1.5" verbs="1" chunks="16" verb_preds="1" concepts="6" domain_bound="3" adjectives="2" abstract_words="5-[9-steady-[relat,sociale,umano],1-trees-[astratto,plant],5-whole-[astratto,evento,attivita],3-brings-[abstract,time,attivita,evento],5-bitches-[astratto,evento,attivita]]/3" modal_advs_adjs="0" untensed_verbs="0" dense_constituents="0" tot_negs="2.5952380952380953" tot_pos="0.11011904761904762" ratio_pos-negs="0.026889534883720933" negative_affect_words="[bitches,ho]" negative_polar_words="[bitches,ho]" positive_polar_words="[steady,rolling,trees,whole,crew]" abstract_eventiv_words="[steady/9,trees/1,whole/5,brings/3,bitches/5]" concrete_words="[trees/1,crew/1,knees/1]">s ody-s steady , rolling up trees , my whole crew brings bitches on they knees , so wassup ho . </sdivars>
</verse_sdi_var>
<verse_sdi_var id="Midnight Cypher at 9.txt_30">
<sdivars id="30" tokens="37" mean_chars_leng="1.9444444444444444" verbs="10" chunks="40" verb_preds="5" concepts="9" domain_bound="7" adjectives="3" abstract_words="9-[3-look-[abstract,time,attivita,evento],5-fuck-[astratto,evento,attivita],14-life-[any,astratto,attivita,cambia,informa,stato,tempo,umano],7-quick-[valutativo],0-come-[abstract,stato],5-ups-[astratto,evento,attivita],3-nice-[abstract,time,attivita,evento],5-dash-[astratto,evento,attivita],7-shady-[evaluative]]/3" modal_advs_adjs="0" untensed_verbs="2" dense_constituents="0.06666666666666667" tot_negs="5.925525525525526" tot_pos="0.3952702702702703" ratio_pos-negs="0.05022513069027359" negative_affect_words="[fuck,whip,shady]" negative_polar_words="[fuck,whip,shady,pistol]" positive_polar_words="[funny,money,quick,cash,dash]" abstract_eventiv_words="[look/3,fuck/5,life/14,quick/7,come/0,ups/5,nice/3,dash/5,shady/7]" concrete_words="[money/1,cash/1,pistol/1]">Don-T look at me funny fuck ya life , I-m out for my money , hitting quick , come ups for some nice cash pistol whip you then it-s road-runner time to dash shady . </sdivars>
</verse_sdi_var>
<verse_sdi_var id="Midnight Cypher at 9.txt_31">
<sdivars id="31" tokens="7" mean_chars_leng="0" verbs="1" chunks="5" verb_preds="1" concepts="3" domain_bound="2" adjectives="0" abstract_words="2-[3-got-[abstract,time,attivita,evento],14-death-[animato,attivita,cambia,evento,informa,stato,tempo]]/1" modal_advs_adjs="0" untensed_verbs="0" dense_constituents="0.5" tot_negs="1.5" tot_pos="0.2" ratio_pos-negs="0.13333333333333333" negative_affect_words="[death]" negative_polar_words="[death,got]" abstract_eventiv_words="[got/3,death/14]" concrete_words="[sock/1]">380 got death in my sock . </sdivars>
</verse_sdi_var>
<verse_sdi_var id="Midnight Cypher at 9.txt_32">
<sdivars id="32" tokens="6" mean_chars_leng="0" verbs="1" chunks="5" verb_preds="1" concepts="2" domain_bound="1" adjectives="1" abstract_words="0-[]/0" modal_advs_adjs="0" untensed_verbs="0" dense_constituents="0" tot_negs="0.6666666666666666" tot_pos="0.3666666666666667" ratio_pos-negs="0.55" positive_polar_words="[key]">better have a key cuz . </sdivars>
</verse_sdi_var>
<verse_sdi_var id="Midnight Cypher at 9.txt_33">
<sdivars id="33" tokens="19" mean_chars_leng="1.9" verbs="3" chunks="20" verb_preds="3" concepts="3" domain_bound="1" adjectives="0" abstract_words="3-[3-got-[abstract,time,attivita,evento],5-background-[astratto,evento,attivita],5-bro-[astratto,evento,attivita]]/2" modal_advs_adjs="0" untensed_verbs="0" dense_constituents="0" tot_negs="0" tot_pos="0.15" ratio_pos-negs="0.07894736842105263" negative_affect_words="[shit,not]" negative_polar_words="[shit,not,not,got]" positive_polar_words="[background]" abstract_eventiv_words="[got/3,background/5,bro/5]" concrete_words="[lock/2,B/2]">I got shit on lock , background you hit it that one bro not , even on B . </sdivars>
</verse_sdi_var>
<verse_sdi_var id="Midnight Cypher at 9.txt_34">
<sdivars id="34" tokens="2" mean_chars_leng="0" verbs="0" chunks="4" verb_preds="0" concepts="1" domain_bound="1" adjectives="0" abstract_words="0-[]/0" modal_advs_adjs="0" untensed_verbs="0" dense_constituents="0" tot_negs="1" tot_pos="0" ratio_pos-negs="1">E . </sdivars>
</verse_sdi_var>
<verse_sdi_var id="Midnight Cypher at 9.txt_35">
<sdivars id="35" tokens="2" mean_chars_leng="0" verbs="0" chunks="4" verb_preds="0" concepts="0" domain_bound="0" adjectives="0" abstract_words="0-[]/0" modal_advs_adjs="0" untensed_verbs="0" dense_constituents="0" tot_negs="0" tot_pos="0" ratio_pos-negs="0">T . </sdivars>
</verse_sdi_var>
<verse_sdi_var id="Midnight Cypher at 9.txt_36">
<sdivars id="36" tokens="33" mean_chars_leng="1.03125" verbs="5" chunks="24" verb_preds="1" concepts="9" domain_bound="6" adjectives="0" abstract_words="9-[9-crook-[oggetto,strumento],5-stealing-[astratto,evento,attivita],5-beats-[astratto,evento,attivita],7-elite-[istituzione],3-conquering-[abstract,time,attivita,evento],9-bitch-[animato,stato],9-call-[attivita,informa],3-looking-[abstract,time,attivita,evento],6-cap-[]]/4" modal_advs_adjs="0" untensed_verbs="3" dense_constituents="0.08333333333333333" tot_negs="7.083333333333334" tot_pos="0.041666666666666664" ratio_pos-negs="0.005134788189987163" negative_affect_words="[crook,stealing,bitch,dick]" negative_polar_words="[crook,stealing,bitch,dick,beats,chest]" positive_polar_words="[elite,tracks,call,looking,cap]" abstract_eventiv_words="[crook/9,stealing/5,beats/5,elite/7,conquering/3,bitch/9,call/9,looking/3,cap/6]" concrete_words="[crook/2,tracks/1,mallets/1,chest/1]">, just a crook , stealing beats for the elite conquering tracks with 40-s and mallets your bitch , with my dick call , her Alice looking for a chest to cap . </sdivars>
</verse_sdi_var>
<verse_sdi_var id="Midnight Cypher at 9.txt_37">
<sdivars id="37" tokens="37" mean_chars_leng="0.625" verbs="6" chunks="30" verb_preds="4" concepts="11" domain_bound="5" adjectives="1" abstract_words="6-[0-wrong-[abstract,stato],5-turn-[astratto,evento,attivita],8-end-[tempo],5-playing-[astratto,evento,attivita],7-familiar-[valutativo],1-octagon-[astratto]]/6" modal_advs_adjs="0" untensed_verbs="1" dense_constituents="0.14285714285714285" tot_negs="2.6244296244296246" tot_pos="0.2954954954954955" ratio_pos-negs="0.09093765049531241" negative_affect_words="[wrong,ass,circle]" negative_polar_words="[wrong,ass,circle,turn,grass,caterpillar]" positive_polar_words="[smoking,ball,like,familiar,squares,step]" abstract_eventiv_words="[wrong/0,turn/5,end/8,playing/5,familiar/7,octagon/1]" concrete_words="[grass/1,billiards/1,squares/1,step/2,octagon/1,circle/1]">wrong turn end in her ass smoking grass , with a caterpillar 8 ball like I-m playing billiards i-m familiar to you , squares , step in the octagon or be out my circle . </sdivars>
</verse_sdi_var>
<verse_sdi_var id="Midnight Cypher at 9.txt_38">
<sdivars id="38" tokens="8" mean_chars_leng="0" verbs="2" chunks="6" verb_preds="1" concepts="2" domain_bound="2" adjectives="1" abstract_words="2-[0-known-[abstract,stato],5-hurt-[astratto,evento,attivita]]/1" modal_advs_adjs="0" untensed_verbs="0" dense_constituents="0" tot_negs="1.125" tot_pos="0.41666666666666663" ratio_pos-negs="0.37037037037037035" negative_affect_words="[hurt]" negative_polar_words="[hurt]" positive_polar_words="[known]" abstract_eventiv_words="[known/0,hurt/5]" concrete_words="[wolves/1]">these wolves are known to hurt ya . </sdivars>
</verse_sdi_var>
<verse_sdi_var id="Midnight Cypher at 9.txt_39">
<sdivars id="39" tokens="13" mean_chars_leng="1.5" verbs="4" chunks="15" verb_preds="2" concepts="3" domain_bound="1" adjectives="0" abstract_words="3-[0-known-[abstract,stato],5-break-[astratto,evento,attivita],3-yay-doer-[abstract,time,attivita,evento]]/1" modal_advs_adjs="1" untensed_verbs="1" dense_constituents="0" tot_negs="3" tot_pos="0.13333333333333333" ratio_pos-negs="0.02962962962962963" negative_affect_words="[game,break]" negative_polar_words="[game,break]" positive_polar_words="[known]" abstract_eventiv_words="[known/0,break/5,yay-doer/3]" concrete_words="[game/2]">game is known to break ya , but i-m a yay-doer . </sdivars>
</verse_sdi_var>
<verse_sdi_var id="Midnight Cypher at 9.txt_40">
<sdivars id="40" tokens="89" mean_chars_leng="1.0853658536585367" verbs="17" chunks="79" verb_preds="8" concepts="24" domain_bound="13" adjectives="3" abstract_words="21-[5-weight-mover-[astratto,evento,attivita],3-making-[abstract,time,attivita,evento],5-taught-[astratto,evento,attivita],5-rob-[astratto,evento,attivita],5-steal-[astratto,evento,attivita],11-deal-[attivita,evento,nquant,sostanza],8-get-[informa,tecno],8-squeal-[evento],5-whining-[astratto,evento,attivita],8-bullshit-[attivita,informa],5-see-[astratto,evento,attivita],5-black-[astratto,evento,attivita],3-left-[abstract,time,attivita,evento],5-driving-[astratto,evento,attivita],14-right-[astratto,attivita,body_part,istituzione,luogo,oggetto,umano],5-bitch-[astratto,evento,attivita],5-tights-[astratto,evento,attivita],5-bitch-[astratto,evento,attivita],3-got-[abstract,time,attivita,evento],10-surprise-[attivita,emotivo,evento],8-try-[attivita,legale]]/7" modal_advs_adjs="1" untensed_verbs="7" dense_constituents="0.05714285714285714" tot_negs="17.632517388978062" tot_pos="0.2922770587398663" ratio_pos-negs="0.015614856389001399" negative_affect_words="[rob,steal,fight,never,bullshit,black,bitch,bitch]" negative_polar_words="[rob,steal,fight,never,bullshit,black,bitch,bitch,never,get,caught,squeal,pigs,pigs,limb,drinking,spitting,got,surprise]" positive_affect_words="[right]" positive_polar_words="[right,bills,taught,deal,save,save,matching,driving,right,tights,matching,eyes,try]" abstract_eventiv_words="[weight-mover/5,making/3,taught/5,rob/5,steal/5,deal/11,get/8,squeal/8,whining/5,bullshit/8,see/5,black/5,left/3,driving/5,right/14,bitch/5,tights/5,bitch/5,got/3,surprise/10,try/8]" concrete_words="[bills/1,pigs/1,pigs/1,rims/1,limb/2,lips/1,eyes/1]">Never will weight-mover making bills always taught to rob and steal fight and deal get caught , never squeal save , the whining for the pigs save , the bullshit for the pigs see you there with the black Mercedes rims matching watch on my left , limb driving with my right , even Though a Ginga been drinking all night spitting all night at that bitch in the tights pretty lips with the matching eyes kinda bitch , you got ta surprise for a second try so . </sdivars>
</verse_sdi_var>
<verse_sdi_var id="Midnight Cypher at 9.txt_41">
<sdivars id="41" tokens="13" mean_chars_leng="0" verbs="2" chunks="11" verb_preds="2" concepts="2" domain_bound="2" adjectives="0" abstract_words="3-[5-leave-[astratto,evento,attivita],1-trees-[astratto,plant],3-get-[abstract,time,attivita,evento]]/1" modal_advs_adjs="0" untensed_verbs="0" dense_constituents="0" tot_negs="0" tot_pos="0.18181818181818182" ratio_pos-negs="0.18181818181818182" negative_affect_words="[not]" negative_polar_words="[not,not,get]" positive_polar_words="[like,trees]" abstract_eventiv_words="[leave/5,trees/1,get/3]" concrete_words="[trees/1]">I leave her like my trees , get high not in it . </sdivars>
</verse_sdi_var>
<verse_sdi_var id="Midnight Cypher at 9.txt_42">
<sdivars id="42" tokens="44" mean_chars_leng="1.4193548387096775" verbs="6" chunks="34" verb_preds="3" concepts="15" domain_bound="8" adjectives="1" abstract_words="3-[8-try-[attivita,legale],5-smashing-[astratto,evento,attivita],12-neck-[body_part,edible,oggetto,strumento,umano]]/7" modal_advs_adjs="2" untensed_verbs="1" dense_constituents="0.11764705882352941" tot_negs="4.673707664884136" tot_pos="0.22459893048128343" ratio_pos-negs="0.03686141908913791" negative_affect_words="[dick,block]" negative_polar_words="[dick,block,dryer,neck,Broken,nose]" positive_polar_words="[try,big,talk,talk,smashing,stripper,deck]" abstract_eventiv_words="[try/8,smashing/5,neck/12]" concrete_words="[dryer/1,fire/2,block/1,neck/2,nose/1,foot/2,deck/1]">If I have_to try probably why my dick dryer than the fire that I walk big talk that I talk back it up with ya , face smashing on the block stripper Neck , Broken Nose , Fire Foot , Deck , Life , </sdivars>
</verse_sdi_var>
</verse_sdi_vars>
</semantic_density>
