<?xml version="1.0" encoding="ISO-8859-1"?>
<semantic_density>

<text_level_sdis id="outs/'Show me Lyrics.txt'" general_sdi="2.116867569623684" mean_char_leng="0.3605731161795237" propositional_negs="0" negative_sentiment_words="15" positive_sentiment_words="42" deep_conceptual_index="155.609756097561" token_rare_words_ratio="0.01556420233463035" token_type_ratio="0.11284046692607004" RID_category_ratio="[14-secondary/0.6666666666666666,[abstract_tought,abstract_tought,abstract_tought,abstract_tought,abstract_tought,concreteness,concreteness,instru_behavior,instru_behavior,instru_behavior,instru_behavior,instru_behavior,temporal_repere,temporal_repere,temporal_repere,temporal_repere,water,water,water,water,water]]" semantic_cohesion="0"></text_level_sdis>
<verse_sdi_vars ids="41">
<verse_sdi_var id="Show me Lyrics.txt_1">
<sdivars id="1" tokens="6" mean_chars_leng="0" verbs="1" chunks="7" verb_preds="0" concepts="1" domain_bound="1" adjectives="0" abstract_words="1-[5-show-[astratto,evento,attivita]]/0" modal_advs_adjs="0" untensed_verbs="1" dense_constituents="0" tot_negs="1" tot_pos="0.16666666666666666" ratio_pos-negs="0.16666666666666666" positive_polar_words="[show]" abstract_eventiv_words="[show/5]">show me Lyrics by Zinc . </sdivars>
</verse_sdi_var>
<verse_sdi_var id="Show me Lyrics.txt_2">
<sdivars id="2" tokens="6" mean_chars_leng="0.8571428571428571" verbs="2" chunks="9" verb_preds="1" concepts="1" domain_bound="1" adjectives="0" abstract_words="1-[5-show-[astratto,evento,attivita]]/0" modal_advs_adjs="0" untensed_verbs="1" dense_constituents="0" tot_negs="2" tot_pos="0.1111111111111111" ratio_pos-negs="0.03888888888888888" negative_polar_words="[gonna]" positive_polar_words="[show]" abstract_eventiv_words="[show/5]">when-re you gonna show me ? </sdivars>
</verse_sdi_var>
<verse_sdi_var id="Show me Lyrics.txt_3">
<sdivars id="3" tokens="6" mean_chars_leng="0.8571428571428571" verbs="2" chunks="9" verb_preds="1" concepts="1" domain_bound="1" adjectives="0" abstract_words="1-[5-show-[astratto,evento,attivita]]/0" modal_advs_adjs="0" untensed_verbs="1" dense_constituents="0" tot_negs="2" tot_pos="0.1111111111111111" ratio_pos-negs="0.03888888888888888" negative_polar_words="[gonna]" positive_polar_words="[show]" abstract_eventiv_words="[show/5]">when-re you gonna show me ? </sdivars>
</verse_sdi_var>
<verse_sdi_var id="Show me Lyrics.txt_4">
<sdivars id="4" tokens="6" mean_chars_leng="0.8571428571428571" verbs="2" chunks="9" verb_preds="1" concepts="1" domain_bound="1" adjectives="0" abstract_words="1-[5-show-[astratto,evento,attivita]]/0" modal_advs_adjs="0" untensed_verbs="1" dense_constituents="0" tot_negs="2" tot_pos="0.1111111111111111" ratio_pos-negs="0.03888888888888888" negative_polar_words="[gonna]" positive_polar_words="[show]" abstract_eventiv_words="[show/5]">when-re you gonna show me ? </sdivars>
</verse_sdi_var>
<verse_sdi_var id="Show me Lyrics.txt_5">
<sdivars id="5" tokens="7" mean_chars_leng="0" verbs="1" chunks="7" verb_preds="1" concepts="0" domain_bound="0" adjectives="1" abstract_words="0-[]/0" modal_advs_adjs="0" untensed_verbs="0" dense_constituents="0" tot_negs="1.1428571428571428" tot_pos="0.14285714285714285" ratio_pos-negs="0.125" positive_polar_words="[good]">how good it is with you . </sdivars>
</verse_sdi_var>
<verse_sdi_var id="Show me Lyrics.txt_6">
<sdivars id="6" tokens="7" mean_chars_leng="0" verbs="2" chunks="9" verb_preds="2" concepts="0" domain_bound="0" adjectives="0" abstract_words="1-[3-get-[abstract,time,attivita,evento]]/0" modal_advs_adjs="0" untensed_verbs="0" dense_constituents="0" tot_negs="1" tot_pos="0.2222222222222222" ratio_pos-negs="0.2222222222222222" negative_polar_words="[gonna,get]" abstract_eventiv_words="[get/3]">when we gonna get it on ? </sdivars>
</verse_sdi_var>
<verse_sdi_var id="Show me Lyrics.txt_7">
<sdivars id="7" tokens="6" mean_chars_leng="0.8571428571428571" verbs="2" chunks="8" verb_preds="1" concepts="1" domain_bound="1" adjectives="0" abstract_words="1-[5-show-[astratto,evento,attivita]]/0" modal_advs_adjs="0" untensed_verbs="1" dense_constituents="0" tot_negs="2" tot_pos="0.125" ratio_pos-negs="0.04375" negative_polar_words="[gonna]" positive_polar_words="[show]" abstract_eventiv_words="[show/5]">when-re you gonna show me . </sdivars>
</verse_sdi_var>
<verse_sdi_var id="Show me Lyrics.txt_8">
<sdivars id="8" tokens="7" mean_chars_leng="0" verbs="1" chunks="7" verb_preds="1" concepts="0" domain_bound="0" adjectives="1" abstract_words="0-[]/0" modal_advs_adjs="0" untensed_verbs="0" dense_constituents="0" tot_negs="1.1428571428571428" tot_pos="0.14285714285714285" ratio_pos-negs="0.125" positive_polar_words="[good]">how good it is with you . </sdivars>
</verse_sdi_var>
<verse_sdi_var id="Show me Lyrics.txt_9">
<sdivars id="9" tokens="8" mean_chars_leng="0" verbs="1" chunks="10" verb_preds="1" concepts="1" domain_bound="1" adjectives="0" abstract_words="1-[8-get-[informa,tecno]]/0" modal_advs_adjs="0" untensed_verbs="0" dense_constituents="0" tot_negs="1" tot_pos="0.1" ratio_pos-negs="0.1" negative_polar_words="[gonna,get]" abstract_eventiv_words="[get/8]">when we gonna a get it off ? </sdivars>
</verse_sdi_var>
<verse_sdi_var id="Show me Lyrics.txt_10">
<sdivars id="10" tokens="6" mean_chars_leng="0.8571428571428571" verbs="2" chunks="8" verb_preds="1" concepts="1" domain_bound="1" adjectives="0" abstract_words="1-[5-show-[astratto,evento,attivita]]/0" modal_advs_adjs="0" untensed_verbs="1" dense_constituents="0" tot_negs="2" tot_pos="0.125" ratio_pos-negs="0.04375" negative_polar_words="[gonna]" positive_polar_words="[show]" abstract_eventiv_words="[show/5]">when-re you gonna show me . </sdivars>
</verse_sdi_var>
<verse_sdi_var id="Show me Lyrics.txt_11">
<sdivars id="11" tokens="7" mean_chars_leng="0" verbs="1" chunks="7" verb_preds="1" concepts="0" domain_bound="0" adjectives="1" abstract_words="0-[]/0" modal_advs_adjs="0" untensed_verbs="0" dense_constituents="0" tot_negs="1.1428571428571428" tot_pos="0.14285714285714285" ratio_pos-negs="0.125" positive_polar_words="[good]">how good it is with you . </sdivars>
</verse_sdi_var>
<verse_sdi_var id="Show me Lyrics.txt_12">
<sdivars id="12" tokens="6" mean_chars_leng="0" verbs="1" chunks="10" verb_preds="1" concepts="0" domain_bound="0" adjectives="1" abstract_words="2-[0-want-[abstract,stato],0-bad-[abstract,stato]]/0" modal_advs_adjs="1" untensed_verbs="0" dense_constituents="0" tot_negs="1.1666666666666667" tot_pos="0.16666666666666666" ratio_pos-negs="0.14285714285714285" negative_affect_words="[bad]" negative_polar_words="[bad]" positive_polar_words="[want]" abstract_eventiv_words="[want/0,bad/0]">i want you so bad . </sdivars>
</verse_sdi_var>
<verse_sdi_var id="Show me Lyrics.txt_13">
<sdivars id="13" tokens="8" mean_chars_leng="0" verbs="2" chunks="10" verb_preds="2" concepts="1" domain_bound="1" adjectives="1" abstract_words="3-[3-make-[abstract,time,attivita,evento],3-feel-[abstract,time,attivita,evento],3-good-[astratto]]/0" modal_advs_adjs="0" untensed_verbs="0" dense_constituents="0" tot_negs="2.125" tot_pos="0.45" ratio_pos-negs="0.21176470588235294" negative_affect_words="[damn]" negative_polar_words="[damn]" positive_polar_words="[feel,good]" abstract_eventiv_words="[make/3,feel/3,good/3]">you make me feel so damn good . </sdivars>
</verse_sdi_var>
<verse_sdi_var id="Show me Lyrics.txt_14">
<sdivars id="14" tokens="6" mean_chars_leng="0" verbs="1" chunks="9" verb_preds="1" concepts="1" domain_bound="1" adjectives="1" abstract_words="3-[0-want-[abstract,stato],3-real-[abstract,time,attivita,evento],3-bad-[astratto]]/0" modal_advs_adjs="1" untensed_verbs="0" dense_constituents="0" tot_negs="1.1666666666666667" tot_pos="0.2777777777777778" ratio_pos-negs="0.23809523809523808" negative_affect_words="[bad]" negative_polar_words="[bad]" positive_polar_words="[want,real]" abstract_eventiv_words="[want/0,real/3,bad/3]">i want you real bad . </sdivars>
</verse_sdi_var>
<verse_sdi_var id="Show me Lyrics.txt_15">
<sdivars id="15" tokens="4" mean_chars_leng="0" verbs="2" chunks="7" verb_preds="2" concepts="0" domain_bound="0" adjectives="0" abstract_words="0-[]/0" modal_advs_adjs="0" untensed_verbs="0" dense_constituents="0" tot_negs="0" tot_pos="0.2857142857142857" ratio_pos-negs="0.2857142857142857" negative_polar_words="[gotta]">gotta have you . </sdivars>
</verse_sdi_var>
<verse_sdi_var id="Show me Lyrics.txt_16">
<sdivars id="16" tokens="6" mean_chars_leng="0" verbs="1" chunks="10" verb_preds="1" concepts="1" domain_bound="1" adjectives="1" abstract_words="2-[0-want-[abstract,stato],3-bad-[astratto]]/0" modal_advs_adjs="1" untensed_verbs="0" dense_constituents="0" tot_negs="2.166666666666667" tot_pos="0.26666666666666666" ratio_pos-negs="0.12307692307692306" negative_affect_words="[bad]" negative_polar_words="[bad]" positive_polar_words="[want]" abstract_eventiv_words="[want/0,bad/3]">i want you so bad . </sdivars>
</verse_sdi_var>
<verse_sdi_var id="Show me Lyrics.txt_17">
<sdivars id="17" tokens="8" mean_chars_leng="0" verbs="2" chunks="10" verb_preds="2" concepts="1" domain_bound="1" adjectives="1" abstract_words="3-[3-make-[abstract,time,attivita,evento],3-feel-[abstract,time,attivita,evento],3-good-[astratto]]/0" modal_advs_adjs="0" untensed_verbs="0" dense_constituents="0" tot_negs="2.125" tot_pos="0.45" ratio_pos-negs="0.21176470588235294" negative_affect_words="[damn]" negative_polar_words="[damn]" positive_polar_words="[feel,good]" abstract_eventiv_words="[make/3,feel/3,good/3]">you make me feel so damn good . </sdivars>
</verse_sdi_var>
<verse_sdi_var id="Show me Lyrics.txt_18">
<sdivars id="18" tokens="6" mean_chars_leng="0" verbs="1" chunks="9" verb_preds="1" concepts="1" domain_bound="1" adjectives="1" abstract_words="3-[0-want-[abstract,stato],3-real-[abstract,time,attivita,evento],3-bad-[astratto]]/0" modal_advs_adjs="1" untensed_verbs="0" dense_constituents="0" tot_negs="1.1666666666666667" tot_pos="0.2777777777777778" ratio_pos-negs="0.23809523809523808" negative_affect_words="[bad]" negative_polar_words="[bad]" positive_polar_words="[want,real]" abstract_eventiv_words="[want/0,real/3,bad/3]">i want you real bad . </sdivars>
</verse_sdi_var>
<verse_sdi_var id="Show me Lyrics.txt_19">
<sdivars id="19" tokens="4" mean_chars_leng="0" verbs="2" chunks="7" verb_preds="2" concepts="0" domain_bound="0" adjectives="0" abstract_words="0-[]/0" modal_advs_adjs="0" untensed_verbs="0" dense_constituents="0" tot_negs="0" tot_pos="0.2857142857142857" ratio_pos-negs="0.2857142857142857" negative_polar_words="[gotta]">gotta have you . </sdivars>
</verse_sdi_var>
<verse_sdi_var id="Show me Lyrics.txt_20">
<sdivars id="20" tokens="6" mean_chars_leng="0.8571428571428571" verbs="2" chunks="9" verb_preds="1" concepts="1" domain_bound="1" adjectives="0" abstract_words="1-[5-show-[astratto,evento,attivita]]/0" modal_advs_adjs="0" untensed_verbs="1" dense_constituents="0" tot_negs="2" tot_pos="0.1111111111111111" ratio_pos-negs="0.03888888888888888" negative_polar_words="[gonna]" positive_polar_words="[show]" abstract_eventiv_words="[show/5]">when-re you gonna show me ? </sdivars>
</verse_sdi_var>
<verse_sdi_var id="Show me Lyrics.txt_21">
<sdivars id="21" tokens="6" mean_chars_leng="0.8571428571428571" verbs="2" chunks="9" verb_preds="1" concepts="1" domain_bound="1" adjectives="0" abstract_words="1-[5-show-[astratto,evento,attivita]]/0" modal_advs_adjs="0" untensed_verbs="1" dense_constituents="0" tot_negs="2" tot_pos="0.1111111111111111" ratio_pos-negs="0.03888888888888888" negative_polar_words="[gonna]" positive_polar_words="[show]" abstract_eventiv_words="[show/5]">when-re you gonna show me ? </sdivars>
</verse_sdi_var>
<verse_sdi_var id="Show me Lyrics.txt_22">
<sdivars id="22" tokens="6" mean_chars_leng="0.8571428571428571" verbs="2" chunks="9" verb_preds="1" concepts="1" domain_bound="1" adjectives="0" abstract_words="1-[5-show-[astratto,evento,attivita]]/0" modal_advs_adjs="0" untensed_verbs="1" dense_constituents="0" tot_negs="2" tot_pos="0.1111111111111111" ratio_pos-negs="0.03888888888888888" negative_polar_words="[gonna]" positive_polar_words="[show]" abstract_eventiv_words="[show/5]">when-re you gonna show me ? </sdivars>
</verse_sdi_var>
<verse_sdi_var id="Show me Lyrics.txt_23">
<sdivars id="23" tokens="7" mean_chars_leng="0" verbs="1" chunks="7" verb_preds="1" concepts="1" domain_bound="1" adjectives="1" abstract_words="1-[3-good-[astratto]]/0" modal_advs_adjs="0" untensed_verbs="0" dense_constituents="0" tot_negs="2.142857142857143" tot_pos="0.2857142857142857" ratio_pos-negs="0.13333333333333333" positive_polar_words="[good]" abstract_eventiv_words="[good/3]">how good it is with you . </sdivars>
</verse_sdi_var>
<verse_sdi_var id="Show me Lyrics.txt_24">
<sdivars id="24" tokens="7" mean_chars_leng="0" verbs="2" chunks="9" verb_preds="2" concepts="1" domain_bound="1" adjectives="0" abstract_words="1-[8-get-[informa,tecno]]/0" modal_advs_adjs="0" untensed_verbs="0" dense_constituents="0" tot_negs="1" tot_pos="0.2222222222222222" ratio_pos-negs="0.2222222222222222" negative_polar_words="[gonna,get]" abstract_eventiv_words="[get/8]">when we gonna get it on ? </sdivars>
</verse_sdi_var>
<verse_sdi_var id="Show me Lyrics.txt_25">
<sdivars id="25" tokens="6" mean_chars_leng="0.8571428571428571" verbs="2" chunks="8" verb_preds="1" concepts="1" domain_bound="1" adjectives="0" abstract_words="1-[5-show-[astratto,evento,attivita]]/0" modal_advs_adjs="0" untensed_verbs="1" dense_constituents="0" tot_negs="2" tot_pos="0.125" ratio_pos-negs="0.04375" negative_polar_words="[gonna]" positive_polar_words="[show]" abstract_eventiv_words="[show/5]">when-re you gonna show me . </sdivars>
</verse_sdi_var>
<verse_sdi_var id="Show me Lyrics.txt_26">
<sdivars id="26" tokens="7" mean_chars_leng="0" verbs="1" chunks="7" verb_preds="1" concepts="1" domain_bound="1" adjectives="1" abstract_words="1-[3-good-[astratto]]/0" modal_advs_adjs="0" untensed_verbs="0" dense_constituents="0" tot_negs="2.142857142857143" tot_pos="0.2857142857142857" ratio_pos-negs="0.13333333333333333" positive_polar_words="[good]" abstract_eventiv_words="[good/3]">how good it is with you . </sdivars>
</verse_sdi_var>
<verse_sdi_var id="Show me Lyrics.txt_27">
<sdivars id="27" tokens="7" mean_chars_leng="0" verbs="2" chunks="9" verb_preds="2" concepts="1" domain_bound="1" adjectives="0" abstract_words="1-[8-get-[informa,tecno]]/0" modal_advs_adjs="0" untensed_verbs="0" dense_constituents="0" tot_negs="1" tot_pos="0.2222222222222222" ratio_pos-negs="0.2222222222222222" negative_polar_words="[gonna,get]" abstract_eventiv_words="[get/8]">when we gonna get it off ? </sdivars>
</verse_sdi_var>
<verse_sdi_var id="Show me Lyrics.txt_28">
<sdivars id="28" tokens="6" mean_chars_leng="0.8571428571428571" verbs="2" chunks="8" verb_preds="1" concepts="1" domain_bound="1" adjectives="0" abstract_words="1-[5-show-[astratto,evento,attivita]]/0" modal_advs_adjs="0" untensed_verbs="1" dense_constituents="0" tot_negs="2" tot_pos="0.125" ratio_pos-negs="0.04375" negative_polar_words="[gonna]" positive_polar_words="[show]" abstract_eventiv_words="[show/5]">when-re you gonna show me . </sdivars>
</verse_sdi_var>
<verse_sdi_var id="Show me Lyrics.txt_29">
<sdivars id="29" tokens="7" mean_chars_leng="0" verbs="1" chunks="7" verb_preds="1" concepts="1" domain_bound="1" adjectives="1" abstract_words="1-[3-good-[astratto]]/0" modal_advs_adjs="0" untensed_verbs="0" dense_constituents="0" tot_negs="2.142857142857143" tot_pos="0.2857142857142857" ratio_pos-negs="0.13333333333333333" positive_polar_words="[good]" abstract_eventiv_words="[good/3]">how good it is with you . </sdivars>
</verse_sdi_var>
<verse_sdi_var id="Show me Lyrics.txt_30">
<sdivars id="30" tokens="6" mean_chars_leng="0" verbs="1" chunks="10" verb_preds="1" concepts="1" domain_bound="1" adjectives="1" abstract_words="2-[0-want-[abstract,stato],3-bad-[astratto]]/0" modal_advs_adjs="1" untensed_verbs="0" dense_constituents="0" tot_negs="2.166666666666667" tot_pos="0.26666666666666666" ratio_pos-negs="0.12307692307692306" negative_affect_words="[bad]" negative_polar_words="[bad]" positive_polar_words="[want]" abstract_eventiv_words="[want/0,bad/3]">i want you so bad . </sdivars>
</verse_sdi_var>
<verse_sdi_var id="Show me Lyrics.txt_31">
<sdivars id="31" tokens="8" mean_chars_leng="0" verbs="2" chunks="10" verb_preds="2" concepts="1" domain_bound="1" adjectives="1" abstract_words="3-[3-make-[abstract,time,attivita,evento],3-feel-[abstract,time,attivita,evento],3-good-[astratto]]/0" modal_advs_adjs="0" untensed_verbs="0" dense_constituents="0" tot_negs="2.125" tot_pos="0.45" ratio_pos-negs="0.21176470588235294" negative_affect_words="[damn]" negative_polar_words="[damn]" positive_polar_words="[feel,good]" abstract_eventiv_words="[make/3,feel/3,good/3]">you make me feel so damn good . </sdivars>
</verse_sdi_var>
<verse_sdi_var id="Show me Lyrics.txt_32">
<sdivars id="32" tokens="6" mean_chars_leng="0" verbs="1" chunks="9" verb_preds="1" concepts="1" domain_bound="1" adjectives="1" abstract_words="3-[0-want-[abstract,stato],3-real-[abstract,time,attivita,evento],3-bad-[astratto]]/0" modal_advs_adjs="1" untensed_verbs="0" dense_constituents="0" tot_negs="1.1666666666666667" tot_pos="0.2777777777777778" ratio_pos-negs="0.23809523809523808" negative_affect_words="[bad]" negative_polar_words="[bad]" positive_polar_words="[want,real]" abstract_eventiv_words="[want/0,real/3,bad/3]">i want you real bad . </sdivars>
</verse_sdi_var>
<verse_sdi_var id="Show me Lyrics.txt_33">
<sdivars id="33" tokens="4" mean_chars_leng="0" verbs="2" chunks="7" verb_preds="2" concepts="0" domain_bound="0" adjectives="0" abstract_words="0-[]/0" modal_advs_adjs="0" untensed_verbs="0" dense_constituents="0" tot_negs="0" tot_pos="0.2857142857142857" ratio_pos-negs="0.2857142857142857" negative_polar_words="[gotta]">gotta have you . </sdivars>
</verse_sdi_var>
<verse_sdi_var id="Show me Lyrics.txt_34">
<sdivars id="34" tokens="6" mean_chars_leng="0" verbs="1" chunks="10" verb_preds="1" concepts="1" domain_bound="1" adjectives="1" abstract_words="2-[0-want-[abstract,stato],3-bad-[astratto]]/0" modal_advs_adjs="1" untensed_verbs="0" dense_constituents="0" tot_negs="2.166666666666667" tot_pos="0.26666666666666666" ratio_pos-negs="0.12307692307692306" negative_affect_words="[bad]" negative_polar_words="[bad]" positive_polar_words="[want]" abstract_eventiv_words="[want/0,bad/3]">i want you so bad . </sdivars>
</verse_sdi_var>
<verse_sdi_var id="Show me Lyrics.txt_35">
<sdivars id="35" tokens="8" mean_chars_leng="0" verbs="2" chunks="10" verb_preds="2" concepts="1" domain_bound="1" adjectives="1" abstract_words="3-[3-make-[abstract,time,attivita,evento],3-feel-[abstract,time,attivita,evento],3-good-[astratto]]/0" modal_advs_adjs="0" untensed_verbs="0" dense_constituents="0" tot_negs="2.125" tot_pos="0.45" ratio_pos-negs="0.21176470588235294" negative_affect_words="[damn]" negative_polar_words="[damn]" positive_polar_words="[feel,good]" abstract_eventiv_words="[make/3,feel/3,good/3]">you make me feel so damn good . </sdivars>
</verse_sdi_var>
<verse_sdi_var id="Show me Lyrics.txt_36">
<sdivars id="36" tokens="6" mean_chars_leng="0" verbs="1" chunks="9" verb_preds="1" concepts="1" domain_bound="1" adjectives="1" abstract_words="3-[0-want-[abstract,stato],3-real-[abstract,time,attivita,evento],3-bad-[astratto]]/0" modal_advs_adjs="1" untensed_verbs="0" dense_constituents="0" tot_negs="1.1666666666666667" tot_pos="0.2777777777777778" ratio_pos-negs="0.23809523809523808" negative_affect_words="[bad]" negative_polar_words="[bad]" positive_polar_words="[want,real]" abstract_eventiv_words="[want/0,real/3,bad/3]">i want you real bad . </sdivars>
</verse_sdi_var>
<verse_sdi_var id="Show me Lyrics.txt_37">
<sdivars id="37" tokens="4" mean_chars_leng="0" verbs="2" chunks="7" verb_preds="2" concepts="0" domain_bound="0" adjectives="0" abstract_words="0-[]/0" modal_advs_adjs="0" untensed_verbs="0" dense_constituents="0" tot_negs="0" tot_pos="0.2857142857142857" ratio_pos-negs="0.2857142857142857" negative_polar_words="[gotta]">gotta have you . </sdivars>
</verse_sdi_var>
<verse_sdi_var id="Show me Lyrics.txt_38">
<sdivars id="38" tokens="6" mean_chars_leng="0" verbs="1" chunks="10" verb_preds="1" concepts="1" domain_bound="1" adjectives="1" abstract_words="2-[0-want-[abstract,stato],3-bad-[astratto]]/0" modal_advs_adjs="1" untensed_verbs="0" dense_constituents="0" tot_negs="2.166666666666667" tot_pos="0.26666666666666666" ratio_pos-negs="0.12307692307692306" negative_affect_words="[bad]" negative_polar_words="[bad]" positive_polar_words="[want]" abstract_eventiv_words="[want/0,bad/3]">i want you so bad . </sdivars>
</verse_sdi_var>
<verse_sdi_var id="Show me Lyrics.txt_39">
<sdivars id="39" tokens="8" mean_chars_leng="0" verbs="2" chunks="10" verb_preds="2" concepts="1" domain_bound="1" adjectives="1" abstract_words="3-[3-make-[abstract,time,attivita,evento],3-feel-[abstract,time,attivita,evento],3-good-[astratto]]/0" modal_advs_adjs="0" untensed_verbs="0" dense_constituents="0" tot_negs="2.125" tot_pos="0.45" ratio_pos-negs="0.21176470588235294" negative_affect_words="[damn]" negative_polar_words="[damn]" positive_polar_words="[feel,good]" abstract_eventiv_words="[make/3,feel/3,good/3]">you make me feel so damn good . </sdivars>
</verse_sdi_var>
<verse_sdi_var id="Show me Lyrics.txt_40">
<sdivars id="40" tokens="6" mean_chars_leng="0" verbs="1" chunks="9" verb_preds="1" concepts="1" domain_bound="1" adjectives="1" abstract_words="3-[0-want-[abstract,stato],3-real-[abstract,time,attivita,evento],3-bad-[astratto]]/0" modal_advs_adjs="1" untensed_verbs="0" dense_constituents="0" tot_negs="1.1666666666666667" tot_pos="0.2777777777777778" ratio_pos-negs="0.23809523809523808" negative_affect_words="[bad]" negative_polar_words="[bad]" positive_polar_words="[want,real]" abstract_eventiv_words="[want/0,real/3,bad/3]">i want you real bad . </sdivars>
</verse_sdi_var>
<verse_sdi_var id="Show me Lyrics.txt_41">
<sdivars id="41" tokens="4" mean_chars_leng="0" verbs="2" chunks="7" verb_preds="2" concepts="0" domain_bound="0" adjectives="0" abstract_words="0-[]/0" modal_advs_adjs="0" untensed_verbs="0" dense_constituents="0" tot_negs="0" tot_pos="0.2857142857142857" ratio_pos-negs="0.2857142857142857" negative_polar_words="[gotta]">gotta have you . </sdivars>
</verse_sdi_var>
</verse_sdi_vars>
</semantic_density>
